django_simpletask_engine.py
django_simpletask/__init__.py
django_simpletask/admin.py
django_simpletask/apps.py
django_simpletask/models.py
django_simpletask/services.py
django_simpletask/views.py
django_simpletask/locale/zh_Hans/LC_MESSAGES/django.mo
django_simpletask/locale/zh_Hans/LC_MESSAGES/django.po
django_simpletask/migrations/__init__.py
django_simpletask-0.3.7.dist-info/LICENSE
django_simpletask-0.3.7.dist-info/METADATA
django_simpletask-0.3.7.dist-info/WHEEL
django_simpletask-0.3.7.dist-info/entry_points.txt
django_simpletask-0.3.7.dist-info/top_level.txt
django_simpletask-0.3.7.dist-info/RECORD
