Metadata-Version: 2.1
Name: django-simpletask
Version: 0.3.7
Summary: Django application provides simple task model, admin, server services and client service.
Author: Zhang XianWei
Author-email: zhangxianwei@zencore.cn
Maintainer: Zhang XianWei
Maintainer-email: zhangxianwei@zencore.cn
License: MIT
Keywords: django abstract model,django simple task
Classifier: Development Status :: 5 - Production/Stable
Classifier: Intended Audience :: Developers
Classifier: Topic :: Software Development :: Libraries :: Python Modules
Classifier: License :: OSI Approved :: MIT License
Classifier: Programming Language :: Python :: 3
Classifier: Programming Language :: Python :: 3 :: Only
License-File: LICENSE
Requires-Dist: Django >=2.2.20
Requires-Dist: bizerror >=0.4.7
Requires-Dist: django-apiview >=0.9.27
Requires-Dist: django-db-lock >=0.5.2
Requires-Dist: fastutils >=0.40.2
Requires-Dist: requests >=2.25.1
